getLucky
