Metadata-Version: 1.0
Name: GetLucky
Version: 1.2.9
Summary: A CLI to quickly set the mood with Songza.
Home-page: http://pypi.python.org/pypi/getlucky/
Author: Tanner Baldus
Author-email: tbaldu285@gmail.com
License: LICENSE.txt
Platform: UNKNOWN
